fabrique_message-2020.7.1.dist-info/RECORD
fabrique_message-2020.7.1.dist-info/WHEEL
fabrique_message-2020.7.1.dist-info/METADATA
fabrique_message-2020.7.1.dist-info/top_level.txt
fabrique_message/message.cpython-36m-x86_64-linux-gnu.so
fabrique_message/__init__.py
